puc8a/__init__.py
puc8a/asm.py
puc8a/assembler.py
puc8a/cc.py
puc8a/compiler.py
puc8a/disassembler.py
puc8a/emitter.py
puc8a/instructions.py
puc8a/simulator.py
puc8a/ppci/__init__.py
puc8a/ppci/api.py
puc8a/ppci/cil.py
puc8a/ppci/common.py
puc8a/ppci/ir.py
puc8a/ppci/runtime.py
puc8a/ppci/arch/__init__.py
puc8a/ppci/arch/arch.py
puc8a/ppci/arch/arch_info.py
puc8a/ppci/arch/asm_printer.py
puc8a/ppci/arch/cc.py
puc8a/ppci/arch/data_instructions.py
puc8a/ppci/arch/effects.py
puc8a/ppci/arch/encoding.py
puc8a/ppci/arch/example.py
puc8a/ppci/arch/generic_instructions.py
puc8a/ppci/arch/isa.py
puc8a/ppci/arch/registers.py
puc8a/ppci/arch/runtime.py
puc8a/ppci/arch/stack.py
puc8a/ppci/arch/target_list.py
puc8a/ppci/arch/token.py
puc8a/ppci/arch/puc8a/__init__.py
puc8a/ppci/arch/puc8a/arch.py
puc8a/ppci/arch/puc8a/instructions-reg.py
puc8a/ppci/arch/puc8a/instructions.py
puc8a/ppci/arch/puc8a/registers.py
puc8a/ppci/binutils/__init__.py
puc8a/ppci/binutils/archive.py
puc8a/ppci/binutils/assembler.py
puc8a/ppci/binutils/debuginfo.py
puc8a/ppci/binutils/disasm.py
puc8a/ppci/binutils/layout.py
puc8a/ppci/binutils/linker.py
puc8a/ppci/binutils/objectfile.py
puc8a/ppci/binutils/outstream.py
puc8a/ppci/binutils/dbg/__init__.py
puc8a/ppci/binutils/dbg/cli.py
puc8a/ppci/binutils/dbg/debug_driver.py
puc8a/ppci/binutils/dbg/debugger.py
puc8a/ppci/binutils/dbg/dummy_driver.py
puc8a/ppci/binutils/dbg/event.py
puc8a/ppci/binutils/dbg/linux64debugdriver.py
puc8a/ppci/binutils/dbg/ptcli.py
puc8a/ppci/binutils/dbg/gdb/__init__.py
puc8a/ppci/binutils/dbg/gdb/client.py
puc8a/ppci/binutils/dbg/gdb/rsp.py
puc8a/ppci/binutils/dbg/gdb/transport.py
puc8a/ppci/cil/__init__.py
puc8a/ppci/cil/io.py
puc8a/ppci/codegen/__init__.py
puc8a/ppci/codegen/burg.grammar
puc8a/ppci/codegen/burg.py
puc8a/ppci/codegen/codegen.py
puc8a/ppci/codegen/dagsplit.py
puc8a/ppci/codegen/flowgraph.py
puc8a/ppci/codegen/instructionscheduler.py
puc8a/ppci/codegen/instructionselector.py
puc8a-0.1.7.dist-info/licenses/LICENSE
puc8a-0.1.7.dist-info/METADATA
puc8a-0.1.7.dist-info/WHEEL
puc8a-0.1.7.dist-info/entry_points.txt
puc8a-0.1.7.dist-info/top_level.txt
puc8a-0.1.7.dist-info/RECORD
