Metadata-Version: 2.4
Name: puc8a
Version: 0.1.7
Summary: Assembler and C compiler for the PUC8a processor
Home-page: http://github.com/wcaarls/puc8a
Author: Wouter Caarls
Author-email: wouter@puc-rio.br
License: GPL-3.0-or-later
Keywords: assembler compiler educational risc processor
Classifier: Development Status :: 4 - Beta
Classifier: Environment :: Console
Classifier: Programming Language :: Python :: 3
Classifier: Topic :: Education
Classifier: Topic :: Software Development :: Assemblers
Classifier: Topic :: Software Development :: Compilers
License-File: LICENSE
Dynamic: author
Dynamic: author-email
Dynamic: classifier
Dynamic: description
Dynamic: description-content-type
Dynamic: home-page
Dynamic: keywords
Dynamic: license
Dynamic: license-file
Dynamic: summary
